only_scraperpy/__init__.py
only_scraperpy/only_scraper.dll
only_scraperpy/only_scraper.dylib
only_scraperpy/only_scraper.so
only_scraperpy-0.1.8.dist-info/LICENSE
only_scraperpy-0.1.8.dist-info/METADATA
only_scraperpy-0.1.8.dist-info/WHEEL
only_scraperpy-0.1.8.dist-info/top_level.txt
only_scraperpy-0.1.8.dist-info/RECORD
