Metadata-Version: 2.1
Name: only_scraperpy
Version: 0.1.8
Summary: Only scrape webpages from rust to python
Home-page: https://github.com/edlugora96/only_scraper_py
Author: Eduardo Gonzalez
Author-email: me@edlugora.com
License: MIT
Classifier: Programming Language :: Python :: 3
Classifier: License :: OSI Approved :: MIT License
Classifier: Operating System :: OS Independent
License-File: LICENSE
